oaicli/__init__.py
oaicli/cli.py
oaicli/oai.py
oaicli/oai_wrappers.py
oaicli-0.2.4.dist-info/LICENSE
oaicli-0.2.4.dist-info/METADATA
oaicli-0.2.4.dist-info/WHEEL
oaicli-0.2.4.dist-info/entry_points.txt
oaicli-0.2.4.dist-info/top_level.txt
oaicli-0.2.4.dist-info/RECORD
