Metadata-Version: 2.1
Name: oaicli
Version: 0.2.4
Summary: A Command Line Interface to Open AI
Author-email: Jonathan Hendler <jonathan@hai.io>
License: Apache License
Keywords: cli,openai,api
Classifier: Programming Language :: Python :: 3
Classifier: License :: OSI Approved :: Apache Software License
Classifier: Operating System :: OS Independent
License-File: LICENSE
Requires-Dist: click >=8.1.7
Requires-Dist: openai >=1.29.0
Requires-Dist: python-dotenv >=1.0.0
Requires-Dist: appdirs >=1.4.4
Requires-Dist: prompt-toolkit >=3.0.40
Provides-Extra: dev
Requires-Dist: black >=23.11.0 ; extra == 'dev'
Requires-Dist: flake8 >=6.1.0 ; extra == 'dev'
